{
  "templates": [
    {
      "name": "homepage",
      "urls": [
        "https://www.mcguirewoods.com"
      ],
      "description": "Main homepage with hero slider, featured people, search, testimonials, culture, statistics, client service, and news",
      "blocks": [
        {
          "name": "carousel-hero",
          "instances": [
            ".home-hero-slider"
          ]
        },
        {
          "name": "cards-people",
          "instances": [
            ".home-team-members-slider"
          ]
        },
        {
          "name": "search-bar",
          "instances": [
            ".home-search-form"
          ]
        },
        {
          "name": "quote-testimonial",
          "instances": [
            ".animated-testimonial"
          ]
        },
        {
          "name": "carousel-culture",
          "instances": [
            ".home-culture-carousel"
          ]
        },
        {
          "name": "columns-stats",
          "instances": [
            ".kb-row-layout-id48671_2dfa34-9f"
          ]
        },
        {
          "name": "accordion-service",
          "instances": [
            ".kt-accordion-id48671_e48fd9-64"
          ]
        },
        {
          "name": "cards-news",
          "instances": [
            ".home-news-carousel"
          ]
        }
      ],
      "sections": [
        {
          "id": "section-1",
          "name": "Hero Slider",
          "selector": ".home-hero-slider-row",
          "style": null,
          "blocks": [
            "carousel-hero"
          ],
          "defaultContent": []
        },
        {
          "id": "section-2",
          "name": "Featured People",
          "selector": ".kb-row-layout-id48671_aaf30d-32",
          "style": null,
          "blocks": [
            "cards-people"
          ],
          "defaultContent": [
            ".home-people-title"
          ]
        },
        {
          "id": "section-3",
          "name": "Search Bar",
          "selector": ".kb-row-layout-id48671_a87e1e-e2",
          "style": "dark",
          "blocks": [
            "search-bar"
          ],
          "defaultContent": []
        },
        {
          "id": "section-4",
          "name": "Testimonial Quote",
          "selector": ".animated-testimonial",
          "style": null,
          "blocks": [
            "quote-testimonial"
          ],
          "defaultContent": []
        },
        {
          "id": "section-5",
          "name": "Culture Section",
          "selector": ".kb-row-layout-id48671_0e626d-d7",
          "style": "dark",
          "blocks": [
            "carousel-culture"
          ],
          "defaultContent": [
            ".kt-adv-heading48671_625277-f0"
          ]
        },
        {
          "id": "section-6",
          "name": "At-a-Glance Statistics",
          "selector": ".kb-row-layout-id48671_2dfa34-9f",
          "style": "dark",
          "blocks": [
            "columns-stats"
          ],
          "defaultContent": []
        },
        {
          "id": "section-8",
          "name": "Client Service",
          "selector": ".kb-row-layout-id48671_1ec135-3a",
          "style": "dark",
          "blocks": [
            "accordion-service"
          ],
          "defaultContent": [
            ".kt-adv-heading48671_7f2fa7-2c",
            ".client-service-image-overlay"
          ]
        },
        {
          "id": "section-9",
          "name": "Spotlight News",
          "selector": ".kb-row-layout-id48671_9bd49a-fb",
          "style": "dark",
          "blocks": [
            "cards-news"
          ],
          "defaultContent": [
            ".kt-adv-heading48671_e75904-08"
          ]
        }
      ]
    },
    {
      "name": "services-landing",
      "urls": [
        "https://www.mcguirewoods.com/services/"
      ],
      "description": "Services landing page with tabbed navigation for practices, industries, and A-Z listing",
      "blocks": [
        {
          "name": "tabs-services",
          "instances": [
            ".services-tabs"
          ]
        }
      ],
      "sections": [
        {
          "id": "section-1",
          "name": "Services Content",
          "selector": [
            ".kb-row-layout-id48672_3b3bec-d5",
            ".kb-row-layout-id48672_2d17b9-98"
          ],
          "style": null,
          "blocks": [
            "tabs-services"
          ],
          "defaultContent": [
            ".kb-row-layout-id48672_3b3bec-d5 h1"
          ]
        }
      ]
    },
    {
      "name": "practice-page",
      "urls": [
        "https://www.mcguirewoods.com/services/practices/business-litigation",
        "https://www.mcguirewoods.com/services/practices/intellectual-property",
        "https://www.mcguirewoods.com/services/practices/data-privacy-cybersecurity"
      ],
      "description": "Practice area detail page with overview, sub-practices, related professionals, and experience highlights",
      "blocks": [
        {
          "name": "hero-practice",
          "instances": [".service-hero-section"]
        },
        {
          "name": "quote-testimonial",
          "instances": [".animated-testimonial"]
        },
        {
          "name": "cards-people",
          "instances": [".wp-block-mgw-people-content-selector"]
        },
        {
          "name": "tabs-related",
          "instances": [".service-related-tabs"]
        },
        {
          "name": "cards-news",
          "instances": [".c-related-posts"]
        }
      ],
      "sections": [
        {
          "id": "section-1",
          "name": "Hero Banner",
          "selector": ".service-hero-section",
          "style": null,
          "blocks": ["hero-practice"],
          "defaultContent": []
        },
        {
          "id": "section-2",
          "name": "Read More Content",
          "selector": ".read-more-content",
          "style": null,
          "blocks": [],
          "defaultContent": [".read-more-content"]
        },
        {
          "id": "section-3",
          "name": "Practice Tagline",
          "selector": [".kb-row-layout-id137_9f4a50-53", ".entry-content > .kb-row-layout-wrap.kt-row-has-bg:nth-of-type(3)"],
          "style": null,
          "blocks": [],
          "defaultContent": [".kb-row-layout-id137_9f4a50-53 p"]
        },
        {
          "id": "section-4",
          "name": "Testimonial Slider",
          "selector": ".animated-testimonial",
          "style": null,
          "blocks": ["quote-testimonial"],
          "defaultContent": []
        },
        {
          "id": "section-5",
          "name": "Team Leaders",
          "selector": [".kb-row-layout-id137_e8b3a0-fa", ".entry-content > .kb-row-layout-wrap:has(.wp-block-mgw-people-content-selector)"],
          "style": null,
          "blocks": ["cards-people"],
          "defaultContent": [".kb-row-layout-id137_e8b3a0-fa h2"]
        },
        {
          "id": "section-6",
          "name": "Related Practices and Industries",
          "selector": [".kb-row-layout-id137_bff9ff-d3", ".entry-content > .kb-row-layout-wrap:has(.service-related-tabs)"],
          "style": "light",
          "blocks": ["tabs-related"],
          "defaultContent": []
        },
        {
          "id": "section-7",
          "name": "News",
          "selector": ".entry-content > .c-related-posts:nth-of-type(1)",
          "style": "dark",
          "blocks": ["cards-news"],
          "defaultContent": []
        },
        {
          "id": "section-8",
          "name": "Insights",
          "selector": ".entry-content > .c-related-posts:nth-of-type(2)",
          "style": "dark",
          "blocks": ["cards-news"],
          "defaultContent": []
        },
        {
          "id": "section-9",
          "name": "Events",
          "selector": ".entry-content > .c-related-posts:nth-of-type(3)",
          "style": "dark",
          "blocks": ["cards-news"],
          "defaultContent": []
        }
      ]
    },
    {
      "name": "industry-page",
      "urls": [
        "https://www.mcguirewoods.com/services/industries/healthcare",
        "https://www.mcguirewoods.com/services/industries/energy",
        "https://www.mcguirewoods.com/services/industries/private-equity"
      ],
      "description": "Industry focus page with sector overview, related practices, key professionals, and industry insights",
      "blocks": [
        {
          "name": "hero-practice",
          "instances": [".service-hero-section"]
        },
        {
          "name": "quote-testimonial",
          "instances": [".animated-testimonial"]
        },
        {
          "name": "carousel-initiatives",
          "instances": [".entry-content > .kb-row-layout-wrap:has(.initatives-slider)"]
        },
        {
          "name": "cards-people",
          "instances": [".wp-block-mgw-people-content-selector"]
        },
        {
          "name": "tabs-related",
          "instances": [".service-related-tabs"]
        },
        {
          "name": "cards-news",
          "instances": [".c-related-posts"]
        }
      ],
      "sections": [
        {
          "id": "section-1",
          "name": "Hero Banner",
          "selector": ".service-hero-section",
          "style": null,
          "blocks": ["hero-practice"],
          "defaultContent": []
        },
        {
          "id": "section-2",
          "name": "Read More Content",
          "selector": ".read-more-content",
          "style": null,
          "blocks": [],
          "defaultContent": [".read-more-content"]
        },
        {
          "id": "section-3",
          "name": "Testimonial Slider",
          "selector": ".entry-content > .kb-row-layout-wrap:has(.animated-testimonial)",
          "style": null,
          "blocks": ["quote-testimonial"],
          "defaultContent": []
        },
        {
          "id": "section-4",
          "name": "Initiatives",
          "selector": ".entry-content > .kb-row-layout-wrap:has(.initatives-slider)",
          "style": "dark",
          "blocks": ["carousel-initiatives"],
          "defaultContent": []
        },
        {
          "id": "section-5",
          "name": "Team Leaders",
          "selector": ".entry-content > .kb-row-layout-wrap:has(.wp-block-mgw-people-content-selector)",
          "style": null,
          "blocks": ["cards-people"],
          "defaultContent": []
        },
        {
          "id": "section-6",
          "name": "Related Services",
          "selector": ".entry-content > .kb-row-layout-wrap:has(.service-related-tabs)",
          "style": "light",
          "blocks": ["tabs-related"],
          "defaultContent": []
        },
        {
          "id": "section-7",
          "name": "News",
          "selector": ".entry-content > .c-related-posts:nth-of-type(1)",
          "style": "dark",
          "blocks": ["cards-news"],
          "defaultContent": []
        },
        {
          "id": "section-8",
          "name": "Insights",
          "selector": ".entry-content > .c-related-posts:nth-of-type(2)",
          "style": "dark",
          "blocks": ["cards-news"],
          "defaultContent": []
        },
        {
          "id": "section-9",
          "name": "Events",
          "selector": ".entry-content > .c-related-posts:nth-of-type(3)",
          "style": "dark",
          "blocks": ["cards-news"],
          "defaultContent": []
        }
      ]
    }
  ]
}
